domainconnectzone/DomainConnectImpl.py
domainconnectzone/DomainConnectTemplates.py
domainconnectzone/__init__.py
domainconnectzone/qsutil.py
domainconnectzone/sigutil.py
domainconnectzone/validate.py
domainconnectzone-4.0.0.dist-info/LICENSE
domainconnectzone-4.0.0.dist-info/METADATA
domainconnectzone-4.0.0.dist-info/WHEEL
domainconnectzone-4.0.0.dist-info/top_level.txt
domainconnectzone-4.0.0.dist-info/RECORD
